django_tenants_url/__init__.py
django_tenants_url/apps.py
django_tenants_url/handlers.py
django_tenants_url/middleware.py
django_tenants_url/models.py
django_tenants_url/permissions.py
django_tenants_url/serializers.py
django_tenants_url/settings.py
django_tenants_url/urls.py
django_tenants_url/utils.py
django_tenants_url/views.py
django_tenants_url-1.0.1.dist-info/AUTHORS
django_tenants_url-1.0.1.dist-info/LICENSE
django_tenants_url-1.0.1.dist-info/METADATA
django_tenants_url-1.0.1.dist-info/WHEEL
django_tenants_url-1.0.1.dist-info/top_level.txt
django_tenants_url-1.0.1.dist-info/RECORD
