Metadata-Version: 2.1
Name: django-tenants-url
Version: 1.0.1
Summary: Django Tenants managed by a single URL.
Home-page: https://tarsil.github.io/django-tenants-url/
Author: Tiago Silva
Author-email: tiago.arasilva@gmail.com
License: MIT
Classifier: Development Status :: 5 - Production/Stable
Classifier: Environment :: Web Environment
Classifier: Framework :: Django
Classifier: Framework :: Django :: 2.2
Classifier: Framework :: Django :: 3.0
Classifier: Framework :: Django :: 3.1
Classifier: Framework :: Django :: 3.2
Classifier: Framework :: Django :: 4.0
Classifier: Framework :: Django :: 4.1
Classifier: Intended Audience :: Developers
Classifier: License :: OSI Approved :: BSD License
Classifier: Operating System :: OS Independent
Classifier: Programming Language :: Python
Classifier: Programming Language :: Python :: 3
Classifier: Programming Language :: Python :: 3.6
Classifier: Programming Language :: Python :: 3.7
Classifier: Programming Language :: Python :: 3.8
Classifier: Programming Language :: Python :: 3.9
Classifier: Programming Language :: Python :: 3.10
Classifier: Programming Language :: Python :: 3 :: Only
Classifier: Topic :: Internet :: WWW/HTTP
Requires-Python: >=3.7
License-File: LICENSE
License-File: AUTHORS
Requires-Dist: bleach (>=4.1.0)
Requires-Dist: django (<4.1,>=2.2)
Requires-Dist: pytz
Requires-Dist: djangorestframework (>=3.13.1)
Requires-Dist: django-tenants (>=3.4.2)
